{
  "word": "mollify",
  "phonetic": "ﾋ埇ﾉ値ﾉｪfaﾉｪ",
  "phoneticUs": "ﾋ埇ﾉ騨人ﾉｪfaﾉｪ",
  "meaning": "v.蟷ｳ諱ｯ",
  "examples": [
    "The investigation was undertaken primarily to mollify pressure groups.",
    "Say something to mollify his anger.",
    "Thus, politicians have looked for other, quicker ways to mollify their constituents.",
    "To mollify private insurers the feds will offer reinsurance above certain levels of liability.",
    "As for vehicles already on the road, Chrysler is working to mollify past customers."
  ]
}