{
  "word": "bilbao",
  "phonetic": "b瑟l藞b蓱藧蓹蕣",
  "phoneticUs": "b瑟l藞ba蕣",
  "meaning": "姣曞皵宸撮剛[瑗跨彮鐗欏寳閮ㄦ腐甯俔",
  "examples": [
    "The family moves first to Switzerland, then slowly across Europe towards Bilbao, before sailing to America.",
    "The Skinny: The Mail Online are reporting that United are chasing Athletic Bilbao midfielder Javi Martinez.",
    "Forwards: David villa (Barcelona), Alvaro Negredo (Sevilla), Fernando Llorente (Athletic Bilbao), Fernando Torres (Chelsea).",
    "The star architect, best known for his Guggenheim museum in Bilbao, Spain, is a hot property.",
    "One caller said they had seen her on a ferry from Portsmouth to Bilbao in Spain."
  ]
}