{
  "word": "accuse",
  "phonetic": "əˈkjuːz",
  "phoneticUs": "əˈkjuːz",
  "meaning": "vt.控告,谴责,非难",
  "examples": [
    "I accuse Consort Xi of adultery. She defiled the harem. Unforgivable.",
    "He laughs loudly when I accuse him of fibbing.",
    "His father would accuse him of neglecting his filial duties.",
    "Politicians accuse the media of talking up the possibility of a riot.",
    "Critics accuse the retail giant of destroying neighborhoods, exploiting its workers and discriminating against female employees."
  ]
}