{
  "word": "adorably",
  "phonetic": "…ЩЋИd…ФЋРr…Щbli",
  "phoneticUs": "…ЩЋИd…ФЋРr…Щbli",
  "meaning": "adv.еіЗжЛЬ",
  "examples": [
    "Especially the babies they are just so adorably cute together.",
    "Fortunately, all of the units are cleverly realized and adorably animated.",
    "She's a very clever cat, followed me adorably, even her poses like mine sometimes.",
    "Adorably, the Doctor has left flowers and jammie dodgers, one of which is half-eaten, at her bedside.",
    "Ben Huh built an online empire of adorably crazy cat pics with his website I Can Has Cheezburger."
  ]
}