{
  "word": "aire",
  "phonetic": "",
  "phoneticUs": "",
  "meaning": "n.亚耳河(英国一河流)",
  "examples": [
    "What's the capacity of the aire storage in your factory?",
    "A report published recently brings bad news about aire pollution.",
    "The aire pressure begins falling accordingly as a typhoon comes near.",
    "Body parts belonging to Ms Blamires were discovered in the River Aire at Shipley on Tuesday.",
    "He plans to build Sand Aire into a business that manages wealth for other families."
  ]
}