{
  "word": "antigone",
  "phonetic": "ænˈtɪɡəni",
  "phoneticUs": "ænˈtɪɡəni",
  "meaning": "n.[希神] 安提歌尼(底比斯王俄狄普斯之女,因违抗禁令而自杀身亡)",
  "examples": [
    "Antigone insists that he cannot save her.",
    "Antigone replies that she will only go out again tonight.",
    "Antigone rejoins that he should have said no; she can say no to anything she thinks vile.",
    "Ms Lane Fox also founded the Go On UK charity to spread digital skills and has her own grant-giving foundation, Antigone, funding charities that target neglected causes."
  ]
}