{
  "word": "apportionment",
  "phonetic": "…ЩЋИp…ФЋР Г(…Щ)nm…Щnt",
  "phoneticUs": "…ЩЋИp…ФЋРr Г(…Щ)nm…Щnt",
  "meaning": "n.еИЖйЕН,еИЖжіЊ,еИЖжСК",
  "examples": [
    "The apportionment of seats in the House of Representatives is based on the population of each state.",
    "The contract defines the apportionment of risks between employer and contractor.",
    "The result of the apportionment of property and debts must be equitable.",
    "The need for liquidity was already addressed in deciding the apportionment among personal risk, market risk and aspirational risk.",
    "Apportionment means you take the net profit and apply a percentage factor derived from sales, property owned and payroll."
  ]
}