{
  "word": "arthroscopy",
  "phonetic": "aːˈθrɒskəpi",
  "phoneticUs": "ɑːrˈθrɑːskəpi",
  "meaning": "n.[医]关节(内窥)镜检查",
  "examples": [
    "A total of 26 second arthroscopy and 28 MRI were analyzed.",
    "Conclusion: Patients commonly required revision hip arthroscopy because of persistent impingement.",
    "Objective to evaluate the role of arthroscopy in the diagnosis and treatment of early tuberculous synovitis.",
    "For example, its Arthroscopy products are used in the repair of soft tissue joint injuries, particularly the knee and shoulder.",
    "He underwent a routine arthroscopy and micro-fracture to two small areas in his right knee and will be non weight-bearing for six to eight weeks."
  ]
}