{
  "word": "aviary",
  "phonetic": "ˈeɪviəri",
  "phoneticUs": "ˈeɪvieri",
  "meaning": "n.(动物园的)大型鸟舍,鸟类饲养场",
  "examples": [
    "The owner said the bird may have escaped through a weak spot in the aviary.",
    "By consolidating the hawks, the new alignment may also unify and perk up the doves in Israel's aviary.",
    "Already he had begun to forget them, and Shepperton soon became an extraordinary aviary, filled with birds of every species.",
    "At the Frankfurt fair, they stood out like an owl in an aviary of tropical parrots.",
    "The three-star Cabanas Hotel is the most informal and family-friendly option, with facilities including a playground, aviary and farmyard."
  ]
}