{
  "word": "inflammatory",
  "phonetic": "瑟n藞fl忙m蓹t(蓹)ri",
  "phoneticUs": "瑟n藞fl忙m蓹t蓴藧ri",
  "meaning": "adj.鐓藉姩鎬х殑",
  "examples": [
    "These ideas may seem tame today, but they were inflammatory in his time.",
    "In general, many lifestyle medicine physicians recommend a plant-based diet鈥攑articularly for people with diabetes or other inflammatory conditions.",
    "That is, the bodies of these happy people are preparing them for bacterial threats by activating the pro-inflammatory response.",
    "The FDA bans the nonsteroidal anti-inflammatory drug (NSAID) Phenylbutazone (Bute) in all food-producing animals.",
    "They will also delve into the safety of older anti-inflammatory medicines such as Aleve and Motrin."
  ]
}