{
  "word": "intersect",
  "phonetic": "ˌɪntəˈsekt",
  "phoneticUs": "ˌɪntərˈsekt",
  "meaning": "vt.横断vi.(直线)相交,交叉",
  "examples": [
    "The lines intersect at right angles.",
    "In particularly wet years, short stretches of an otherwise dry stream-bed may have flowing water because the water table rises to intersect the land surface.",
    "If the water table intersect the land surface, groundwater will flow out onto the surface at springs, whether to be collected there or to subsequently flow farther along a drainage.",
    "Tsutsumi is a living demonstration of how money and political power intersect in present day Japan.",
    "This is an example of where the several issues that I work on intersect so nicely."
  ]
}