{
  "word": "piranha",
  "phonetic": "pɪˈrɑːnə",
  "phoneticUs": "pəˈrænə",
  "meaning": "n.[鱼]水虎鱼(产于南美产的一种小鱼)",
  "examples": [
    "There are more than 60 kinds of Piranha fish.",
    "Most piranha species are omnivores and scavengers.",
    "Time for the ultimate killer's test: How would the piranha react to my duck?",
    "Mr. NAYDER: This is Piranha Man from Pakistan, one of our most requested unpopular artists.",
    "It features 3 new weapons: Piranha assault shotgun, Acolyte pistol, and Typhoon light machine gun."
  ]
}