{
  "word": "priceless",
  "phonetic": "ЋИpra…™sl…Щs",
  "phoneticUs": "ЋИpra…™sl…Щs",
  "meaning": "adj.жЧ†дїЈзЪД,жЮБиіµйЗНзЪД",
  "examples": [
    "They are priceless, unique and irreplaceable.",
    "The house is crammed with priceless furniture and works of art.",
    "A number of priceless works of art were stolen from the gallery.",
    "The third priceless moment takes longer to notice because it happens quietly over time.",
    "It has not been easy, but at least we are all together, and that is priceless."
  ]
}