{
  "word": "probationer",
  "phonetic": "pr…ôňąbe…™ É…ôn…ô(r)",
  "phoneticUs": "pro äňąbe…™ É…ôn…ôr",
  "meaning": "n.ŤĮēŤĮĽÁĒü,ÁľďŚąĎÁäĮ",
  "examples": [
    "Methods Survey among probationer nurses was performed by questionnaires.",
    "Objective To probe the mental health situation of probationer nurses, and raise the mental health Level of nurses.",
    "Objective To understand the occurrence situation of needling damage of probationer nurses during probation. To probe the occurrence link.",
    "If a probationer still gets into trouble, the county can now punish him in ways short of returning him to prison.",
    "It is also warning that some trainee teachers face difficulty in finding a school placement despite assurances in the agreement that every \"probationer\" will get one year's training."
  ]
}