{
  "word": "quarterdeck",
  "phonetic": "ˈkwɔːtədek",
  "phoneticUs": "ˈkwɔːrtərdek",
  "meaning": "n.后甲板",
  "examples": [
    "Do you give me the lie on my own quarterdeck?",
    "The captain stood towering on the quarterdeck with his gaze fixed on the unfortunate Wellard, who shrank visibly away from him.",
    "Quarterdeck corp. is planning a series of major upgrades to its web-compass search engine--integrating advanced agent and filtering technologies--in an attempt to improve the relevance of searches."
  ]
}