{
  "word": "cedi",
  "phonetic": "ˈseɪdi",
  "phoneticUs": "ˈseɪdɪ",
  "meaning": "n.塞地(加纳共和国的货币单位,其纸币)",
  "examples": [
    "CEDI unit will perform a integral demineralization process of electrolysis, electrodialysis and ion-exchange.",
    "But this measure, by creating a dollar black market, had the opposite effect: last year the cedi lost more than half its value.",
    "The external value of the local currency, the cedi, has dropped precipitously from 1.4 cedis to the dollar in January 2.2 cedis to the dollar in July -- a drop of 57% in terms of the local currency.",
    "The Ghanaian cedi, too, looks overvalued."
  ]
}