{
  "word": "coalfield",
  "phonetic": "ˈkəʊlfiːld",
  "phoneticUs": "ˈkoʊlfiːld",
  "meaning": "n.煤田",
  "examples": [
    "The park lies on top of a coalfield.",
    "The Panian coalfield is being mined using open-pit methods.",
    "The Permian in Huainan coalfield is a set of deltaic coastal deposition.",
    "He sent his son to investigate the Preece property, a 5, 000-hectare coalfield in Kentucky.",
    "He sent his son to investigate the Preece property, a 12, 500-acre coalfield in Kentucky."
  ]
}