{
  "word": "concisely",
  "phonetic": "k…ônňąsa…™sli",
  "phoneticUs": "k…ônňąsa…™sli",
  "meaning": "adv.ÁģÄśėéŚúį",
  "examples": [
    "He'd delivered his report clearly and concisely.",
    "Communicate Consistently, Clearly, concisely.",
    "Communicates Consistently, Clearly, concisely.",
    "To put it concisely, I think what people may be observing is very elastic labor demand.",
    "She presents examples of the damsel in distress trope in video games concisely and effectively."
  ]
}