{
  "word": "consciously",
  "phonetic": "ˈkɒnʃəsli",
  "phoneticUs": "ˈkɑːnʃəsli",
  "meaning": "adv.有意识地,自觉地",
  "examples": [
    "Part of me was very frightened and I consciously had to get a grip on myself.",
    "A previous study noted that dolphins always consciously control their breathing.",
    "She was self-consciously aware of his stare.",
    "This would mean countries with current account surpluses adopting policies that would consciously reduce these surpluses.",
    "There is no grand conspiracy here, and nobody is consciously lying, I would bet."
  ]
}