{
  "word": "contaminant",
  "phonetic": "kənˈtæmɪnənt",
  "phoneticUs": "kənˈtæmɪnənt",
  "meaning": "n.致污物,污染物",
  "examples": [
    "Experts say testing needs to be done on each contaminant to determine the long-term effects on humans.",
    "High purity water systems are primarily composed of austenitic stainless steel (ss) materials due to their corrosion resistant and contaminant free properties.",
    "Each of the membrane technologies is essentially a filtration process in which contaminant ions are filtered from solution using a membrane with very small water passages.",
    "Shuanghui apologized on its website and said it discontinued partnerships with producers using the contaminant.",
    "For example, contaminant removal may include the separation of unwanted materials like electronics, PVC and minerals."
  ]
}