{
  "word": "corrugator",
  "phonetic": "ﾋ𡌛ﾉ藩甚ﾉ厖庫｡eﾉｪtﾉ决",
  "phoneticUs": "ﾋ𡌛ﾉ藩甚ﾉ厖庫｡eﾉｪtﾉ决",
  "meaning": "n.[隗｣]逧ｱ逵芽ｌ",
  "examples": [
    "Corrugator supercilii can be divided into three types, the transversal, the diagonal and the diagonal separable types.",
    "When amputating the corrugator, we should operate carefully under direct vision to avoid damaging superaortibal nerve.",
    "Results Corrugator supercilii can be divided into three types, the transversal, the diagonal and the diagonal separable types in which the major one is the diagonal."
  ]
}