{
  "word": "cruelly",
  "phonetic": "ˈkruːəli",
  "phoneticUs": "ˈkruːəli",
  "meaning": "adv.残忍地,残酷地",
  "examples": [
    "I was cruelly deceived.",
    "We find ourselves cruelly cut off from the wireless world.",
    "Tom said with genuine anguish, \"I crave your indulgence; my nose itcheth cruelly.\"",
    "Though her hopes are cruelly dashed, new ones are awakened by her sensitive, literary colleague, Chu.",
    "As cruelly inevitable as the earthquake was unforeseeable, winter may be an even bigger disaster."
  ]
}