{
  "word": "emulate",
  "phonetic": "ˈemjuleɪt",
  "phoneticUs": "ˈemjuleɪt",
  "meaning": "n.仿效",
  "examples": [
    "Sons are traditionally expected to emulate their fathers.",
    "They may be able to emulate the dripping sound of a crosswalk, or the buzz of a power tool.",
    "But before we try to emulate geniuses or encourage our children to do so we should note that some of the things we learn from them may prove unpalatable.",
    "And what about society s youth that strives desperately to emulate Hollywood s stars?",
    "So, if you want security after the checks stop coming, emulate oilman John D."
  ]
}