{
  "word": "enlarge",
  "phonetic": "…™nňąl…Ďňźd í",
  "phoneticUs": "…™nňąl…Ďňźrd í",
  "meaning": "v.śČ©Ś§ß,śĒĺŚ§ß",
  "examples": [
    "Reading will enlarge your vocabulary.",
    "There are plans to enlarge the recreation area.",
    "He didn't enlarge on the form that the interim government and assembly would take.",
    "Francis was now in a position to enlarge his group, to spread his message.",
    "We must enlarge our purpose for creation to help us discover what really needs our attention."
  ]
}