{
  "word": "enshrine",
  "phonetic": "ɪnˈʃraɪn",
  "phoneticUs": "ɪnˈʃraɪn",
  "meaning": "vt.入庙祀奉,铭记",
  "examples": [
    "It is supposed to enshrine the words that actually mean things.",
    "The 'forest Principles' and Chapter 11 of Agenda 21 enshrine the commitments made by nations in the forestry domain.",
    "But, as a former war reporter myself, I recoil from the mawkish sentimentality with which we enshrine our casualties.",
    "The legislation, Mr MacAskill said, would \"enshrine in law a victim's right to damages and compensation\".",
    "It wanted a civil service act to enshrine the non-partisan rights and duties of officials."
  ]
}