{
  "word": "felix",
  "phonetic": "ˈfiːlɪks",
  "phoneticUs": "ˈfiːlɪks",
  "meaning": "n.费利克斯(m.)",
  "examples": [
    "Felix watched his men move like soldiers, spreading out into two teams.",
    "You needn't worry; I'll be ready to greet them. Meanwhile, I'm off to discuss the Fowler's party with Felix.",
    "When looking at a pair of old chopsticks, most people would see nothing but waste. But Felix Bock would see boxes, tables, shelves and so on.",
    "The film also won the best screenplay award for Carl Joos and Felix van Groeningen.",
    "Felix Vega stays below the speed limit and comes to a complete halt at stop signs."
  ]
}