{
  "word": "flowerpot",
  "phonetic": "ˈflaʊəpɒt",
  "phoneticUs": "ˈflaʊərpɑːt",
  "meaning": "n.花盆,花钵",
  "examples": [
    "I'm trying to put the flowerpot on the windowsill.",
    "A sea kayaker navigates the rocks around Flowerpot Island in Ontario's Fathom Five National Marine Park.",
    "He might as well plant an oak in a flowerpot, and expect it to thrive, as imagine he can restore her to vigour in the soil of his shallow cares!",
    "There was a flowerpot on the windowsill, and in it a small, dazzlingly red rose.",
    "The group's inventions include a simple flower that emerges from its flowerpot only when a user's long-distance partner comes online."
  ]
}