{
  "word": "forfeiture",
  "phonetic": "ˈfɔːfɪtʃə(r)",
  "phoneticUs": "ˈfɔːrfɪtʃər",
  "meaning": "n.丧失,没收物,罚款,",
  "examples": [
    "He was deep in debt and faced with forfeiture of his property.",
    "The forfeiture of illegally obtained profits is part of the penalty.",
    "Instead, he is suing to have the Texas civil asset forfeiture law struck down.",
    "Vessels caught in violation of the law face seizure and forfeiture of their equipment and boat.",
    "There are more than 350 laws and violations that can subject property to government asset forfeiture."
  ]
}