{
  "word": "fragility",
  "phonetic": "fr蓹藞d蕭瑟l蓹ti",
  "phoneticUs": "fr蓹藞d蕭瑟l蓹ti",
  "meaning": "n.鑴嗗急,铏氬急",
  "examples": [
    "By mid-1988 there were clear indications of the extreme fragility of the Right-wing coalition.",
    "Steel's fragility at low temperatures first became a major concern during the Second World War.",
    "We're served up an endless stream of advice on \"how to survive your 40s\", as if we're in the endurance stage of a slow limp toward fragility.",
    "Lord Rees raises concerns about the social fragility and lack of resilience in our technology-dependent society.",
    "Is business investment based on the fragility of the economy -- is it governed by that?"
  ]
}