{
  "word": "semantics",
  "phonetic": "sɪˈmæntɪks",
  "phoneticUs": "sɪˈmæntɪks",
  "meaning": "n.[语]语义学",
  "examples": [
    "This is just semantics.",
    "So far we have been looking at some of the core areas of linguistics, like syntax, phonology, semantics.",
    "Some of the semantics have changed.",
    "Mr. Kurzweil's goal is to enable Google's search engine to read, hear and understand human semantics.",
    "Along the way, the social environment is adding context or semantics to the information."
  ]
}