{
  "word": "sensitise",
  "phonetic": "ˈsensətaɪz",
  "phoneticUs": "",
  "meaning": "v.<主英> =sensitize",
  "examples": [
    "The result of the shrinkage Worldwide Awards are multi-disciplinary, multi-use posters which explore, divulge, foster, sensitise and awaken both shrinkage culture and experience.",
    "Cases like this have caused outrage in India, with many calling for the need to sensitise the police.",
    "The aim of the project, which is taking place in cities across the continent, is to sensitise people to the meaning of cultural heritage and interest them in the preservation of ancient monuments."
  ]
}