{
  "word": "separation",
  "phonetic": "ˌsepəˈreɪʃn",
  "phoneticUs": "ˌsepəˈreɪʃn",
  "meaning": "n.分离,分开",
  "examples": [
    "They agreed to a trial separation.",
    "She wondered if Harry had been unfaithful to her during this long separation.",
    "Separation from his friends made him sad.",
    "One reason for this separation of services is because the two are charged for differently.",
    "Quinn told reporters that any separation project would have to address economic and safety concerns."
  ]
}