{
  "word": "shelve",
  "phonetic": "ʃelv",
  "phoneticUs": "ʃelv",
  "meaning": "vt.置于架子上,缓议,搁置,解雇vi.倾斜",
  "examples": [
    "They shelve the letters and do not give them due consideration.",
    "The inverse of shelve is unshelve.",
    "To set aside the changes, run bzr shelve.",
    "As for McKinley's 42-volt turbocharging system, BorgWarner decided to shelve the idea for the time being.",
    "Challenge law enforcement agencies to start by believing and to investigate, not shelve, these crimes."
  ]
}