{
  "word": "splendidly",
  "phonetic": "ˈsplendɪdli",
  "phoneticUs": "ˈsplendɪdli",
  "meaning": "adv.壮观地,华丽地",
  "examples": [
    "You all played splendidly.",
    "The iron teakettle was hissing splendidly over live coals.",
    "I have heard him tell people that we get along splendidly.",
    "Such a quibble aside, it is undeniable that \"Models Behaving Badly\" itself performs splendidly.",
    "They are the fourth generation of their family to run Gerdau S.A. and run it splendidly."
  ]
}