{
  "word": "vilification",
  "phonetic": "틟v톩l톩f톩틛ke톩툮n",
  "phoneticUs": "틟v톩l톩f톩틛ke톩툮n",
  "meaning": "n.劉뫧댐,疸쇇쨗,放쫻쌳",
  "examples": [
    "Conchita did not deserve the vilification she had been subjected to.",
    "An attempt to destroy a reputation; vilification or slander.",
    "The glorification of Team Refugees and the vilification of refugees coexist.",
    "Once Brahms was set up as Wagner's adversary, he drew vilification or adoration according to allegiance.",
    "No coalition to defeat terrorism can include countries that countenance campaigns of hate and vilification."
  ]
}