{
  "word": "unspent",
  "phonetic": "ˌʌnˈspent",
  "phoneticUs": "ʌnˈspent",
  "meaning": "adj.没有用完的,未耗尽的,仍有效的",
  "examples": [
    "Now, more than ever, their money is sitting in Banks, unspent.",
    "Wang's report explains where that money is coming from, and why there is even more of that cash that remains unspent.",
    "My goal is to shave time off that deadline by bringing home enough unspent \"travel money\" to make a full months 'car payment.",
    "And much regional and social fund money goes unspent because recipients cannot find matching funds.",
    "Unspent HSA funds can be used for health expenses in later years, or for anything in retirement."
  ]
}