{
  "word": "handedness",
  "phonetic": "ˈhændɪdnəs",
  "phoneticUs": "ˈhændɪdnəs",
  "meaning": "n.用右手或左手的习惯",
  "examples": [
    "They have been accused of secrecy and high-handedness in their dealings.",
    "What mechanisms control handedness and keep left-handedness rare?",
    "Sporting advantage notwithstanding, therefore, the existence of left-handedness poses a problem for biologists.",
    "They looked at homicide-rates and the frequency of left-handedness, and found they appeared to be linked.",
    "But the Eipo had around three homicides per 1, 000 people and a left-handedness rate of 20%."
  ]
}