{
  "word": "headhunter",
  "phonetic": "ˈhedhʌntə(r)",
  "phoneticUs": "ˈhedhʌntər",
  "meaning": "n.猎取人头的蛮人",
  "examples": [
    "\"The traditional rule was it's safer to stay where you are, but that's been fundamentally inverted,\" says one headhunter.",
    "\"How much worse can the 'headhunter' name be?",
    "What do you do when a headhunter calls you unexpectedly?",
    "In 1985 a headhunter landed him a job at American Hospital Supply in Santa Ana, Calif.",
    "When his job as a corporate headhunter evaporated in late 2008, he turned to the bottle."
  ]
}