{
  "word": "ob",
  "phonetic": "",
  "phoneticUs": "",
  "meaning": "鄂毕湾(靠苏联西西伯利亚北岸)",
  "examples": [
    "The objective is to study the applical value on medical OB glue preventing bile leadage during laparoscopic cholecystectomy.",
    "Your ob-gyn or midwife is also a good resource.",
    "Some women prefer to work with a midwife others prefer their ob-gyn.",
    "\"Fertility is absolutely a wild card, \" says Laurie Green, an OB-GYN in San Francisco.",
    "And Sir Paul McCartney wrapped up proceedings with a jaunty crowd participation version of Ob-La-Di, Ob-La-Da."
  ]
}