{
  "word": "offering",
  "phonetic": "ˈɒfərɪŋ",
  "phoneticUs": "ˈɔːfərɪŋ",
  "meaning": "n.提供,奉献物,献礼,祭品",
  "examples": [
    "They wooed customers by offering low interest rates.",
    "We take pride in offering you the highest standards.",
    "The number of companies offering them work increased.",
    "The Corporate Market segment operates an ICT services and offering end-to-end solutions in infrastructure and network-related.",
    "Last year the government began offering grants to disabled people with aspirations to enter politics."
  ]
}