{
  "word": "lall",
  "phonetic": "læl",
  "phoneticUs": "læl",
  "meaning": "v.[语]把/r/音读成/l/音",
  "examples": [
    "Until lall dreams has broken, didn't see your tears and regret.",
    "JESSICA LALL, a model, was shot dead at a posh party in Delhi in 1999.",
    "Instead, Lall found that there were relatively few severe events compared to such flood-ravaged years as 2002, 2003, and 2007.",
    "Pawan's father and Hero Honda Chairman Brijmohan Lall Munjal, 85, insists that the rural touch is nothing new.",
    "Marie Lall is a South Asia specialist at the Institute of Education, University of London, and an associate fellow at Chatham House."
  ]
}