{
  "word": "leash",
  "phonetic": "liːʃ",
  "phoneticUs": "liːʃ",
  "meaning": "n.拴狗颈的皮带,控制,约束vt.以皮带束缚,束缚",
  "examples": [
    "One Sunday he began trying to teach the two puppies to walk on a leash.",
    "You just have to keep him on a tight leash.",
    "You, dear reader, encounter a Rottweiler, not on a leash but loose. How do you react?",
    "Not even Roland Emmerich can keep the hangdog spirit of Reno on a leash.",
    "Owners can be ordered to leash or muzzle their dogs and to take training courses."
  ]
}