{
  "word": "lees",
  "phonetic": "liːz",
  "phoneticUs": "liːz",
  "meaning": "n.pl.酒糟,渣滓",
  "examples": [
    "The lost car of the Lees was found abandoned in the woods off the highway.",
    "Or at least, you don't have to tell that to Joanne Lees.",
    "Soon after the marriage, Hyde-Lees realised she had a particular talent for channelling ghosts.",
    "Shortly after acquiring the tower at the age of 51, Yeats married Georgie Hyde-Lees, a 25-year-old Englishwoman.",
    "So, Lees can expect to be talking to Steve a lot in the coming months."
  ]
}