{
  "word": "licenser",
  "phonetic": "ˈlaɪsnsə(r)",
  "phoneticUs": "ˈlaɪsənsər",
  "meaning": "n.认可证颁发者(尤指批准书籍出版或戏剧演出的官员)",
  "examples": [
    "Licenser is also the producer of the data contained in the Database (as defined below).",
    "With the combining of technology standard and patent, the technology standard's patent pool is becoming more and more important patent licenser.",
    "The ex officio license of the new inventions and creations accomplished by the licenser in the performance of contracts or any other provisions;"
  ]
}