{
  "word": "lucinda",
  "phonetic": "luːˈsɪndə",
  "phoneticUs": "luˈsɪndə",
  "meaning": "n.露辛达(Lucy的异体)(f.)",
  "examples": [
    "There is real intensity as Lucinda Broadbridge strikingly conveys in the fourth of the Casos Sonnets.",
    "Since we last spoke, she's launched Lucinda Yates Jewelry Collection.",
    "\"... a good solution for unrequited love is, of course, new love.\" –Lucinda Rosenfeld",
    "Also lined up are Apprentice contestant Lucinda Ledgerwood, actor Phil Daniels and singer Katie Melua.",
    "\"It's like night and day, \" said Lucinda Roy, a creative-writing professor who taught Mr. Cho."
  ]
}