{
  "word": "deportment",
  "phonetic": "d톩틛p톖틣tm톛nt",
  "phoneticUs": "d톩틛p톖틣rtm톛nt",
  "meaning": "n.發꺿쟠,疸쮡속",
  "examples": [
    "It is this third city that accounts for New York's high-strung disposition, its poetical deportment, its dedication to the arts, and its incomparable achievements.",
    "One's deportment is dignified.",
    "If you have the time, go for deportment classes.",
    "You will garner some basic deportment that others pick up on.",
    "Following Burch for a day provides an almost maddening lesson in maintaining the perfect deportment while balancing late-night fittings, lost homework and an endless stream of meetings."
  ]
}