{
  "word": "desecration",
  "phonetic": "ˌdesɪˈkreɪʃn",
  "phoneticUs": "ˌdesɪˈkreɪʃn",
  "meaning": "n.亵渎神圣,污辱",
  "examples": [
    "The whole area has been shocked by the desecration of the cemetery.",
    "Desecration, and so forth, and lectured you on dignity and sanctity.",
    "Desecration of the time, the negative of its debt, it will be severely punished by it!",
    "The continued malicious desecration of Joshua Tree National Park has now affected archeological sites.",
    "Church warden Steven Stanworth said he considered the thefts a desecration of the ground."
  ]
}