{
  "word": "diverse",
  "phonetic": "daɪˈvɜːs",
  "phoneticUs": "daɪˈvɜːrs",
  "meaning": "adj.不同的,变化多的",
  "examples": [
    "Cuba is a composite of diverse traditions and people.",
    "The company owns a very diverse library of Arabic music.",
    "It is geographically more diverse than any other continent.",
    "The diverse representation at the event gave a fascinating insight into different global cinema cultures.",
    "The last three days of riding highlighted just how diverse La Route Verte can be."
  ]
}