{
  "word": "gcse",
  "phonetic": "ňĆd íiňź siňź es ňąiňź",
  "phoneticUs": "ňĆd íiňź siňź es ňąiňź",
  "meaning": "General Certificate of Secondary Education",
  "examples": [
    "He's doing German at GCSE.",
    "The study looked at GCSE results in both sorts of schools.",
    "Suzi is now re-taking GCSE English and plans to go to college.",
    "The strike will now disrupt students as it coincides with GCSE and A-Level examinations.",
    "Controlled assessment is GCSE coursework which is sat in the classroom under strict supervision and marked by teachers."
  ]
}