{
  "word": "recant",
  "phonetic": "rɪˈkænt",
  "phoneticUs": "rɪˈkænt",
  "meaning": "v.放弃",
  "examples": [
    "White House officials ordered Williams to recant.",
    "For form’s sake, Luther was first invited to recant.",
    "Editorials would demand that he either recant or retire from public life.",
    "If it happens, I hereby recant this story and become a believer in predictions.",
    "However, Bishop Williamson has indicated he will not immediately comply with the Pope's demand that he recant."
  ]
}