{
  "word": "neurophysiology",
  "phonetic": "ˌnjʊərəʊfɪziˈɒlədʒi",
  "phoneticUs": "ˌnʊroʊfɪziˈɑːlədʒi",
  "meaning": "n.神经生理学",
  "examples": [
    "This is the homepage for Clinical Neurophysiology.",
    "Find a neurologist who specializes in the neurophysiology of hyperhidrosis.",
    "The results were published in the July issue of the Journal of Neurophysiology.",
    "Fabrizio Benedetti, professor of neurophysiology at the University of Turin Medical School, Italy, warned that dopamine may not be the only chemical involved with the placebo effect."
  ]
}