{
  "word": "newfound",
  "phonetic": "ˈnjuːfaʊnd",
  "phoneticUs": "ˌnuːˈfaʊnd",
  "meaning": "adj.新发现的,新得到的",
  "examples": [
    "She savoured her newfound freedom.",
    "His friends have a newfound sense of patriotism.",
    "A rush of newfound happiness washed over her.",
    "Finding a mix of total relaxation and newfound inspiration on his tech-free vacation, Tristan Wright agreed.",
    "Faith-based groups are bringing hope to pockets of despair, with newfound support from the Federal Government."
  ]
}