{
  "word": "nitwit",
  "phonetic": "ˈnɪtwɪt",
  "phoneticUs": "ˈnɪtwɪt",
  "meaning": "n.笨人,傻子",
  "examples": [
    "Let's go and leave the nitwit alone.",
    "Would you stop doing those nitwit tricks?",
    "Anything that can't be pronounced stops the verbal music, makes the reader stumble and marks the writer as a nitwit.",
    "One network nitwit even said the market could have only gone up the way it did today because someone somewhere knows that there already is a deal that will save the world."
  ]
}